LICENSE.txt
MANIFEST.in
README.rst
setup.py
usienarl/__init__.py
usienarl/agent.py
usienarl/config.py
usienarl/environment.py
usienarl/experiment.py
usienarl/interface.py
usienarl/model.py
usienarl/volley.py
usienarl.egg-info/PKG-INFO
usienarl.egg-info/SOURCES.txt
usienarl.egg-info/dependency_links.txt
usienarl.egg-info/requires.txt
usienarl.egg-info/top_level.txt
usienarl/agents/__init__.py
usienarl/agents/ddpg_agent.py
usienarl/agents/deep_expected_sarsa_agent_boltzmann.py
usienarl/agents/deep_expected_sarsa_agent_dirichlet.py
usienarl/agents/deep_expected_sarsa_agent_epsilon_greedy.py
usienarl/agents/deep_q_learning_agent_boltzmann.py
usienarl/agents/deep_q_learning_agent_dirichlet.py
usienarl/agents/deep_q_learning_agent_epsilon_greedy.py
usienarl/agents/deep_sarsa_agent_boltzmann.py
usienarl/agents/deep_sarsa_agent_dirichlet.py
usienarl/agents/deep_sarsa_agent_epsilon_greedy.py
usienarl/agents/double_deep_q_learning_agent_boltzmann.py
usienarl/agents/double_deep_q_learning_agent_dirichlet.py
usienarl/agents/double_deep_q_learning_agent_epsilon_greedy.py
usienarl/agents/dueling_deep_q_learning_agent_boltzmann.py
usienarl/agents/dueling_deep_q_learning_agent_dirichlet.py
usienarl/agents/dueling_deep_q_learning_agent_epsilon_greedy.py
usienarl/agents/ppo_agent.py
usienarl/agents/random_agent.py
usienarl/agents/tabular_expected_sarsa_agent_boltzmann.py
usienarl/agents/tabular_expected_sarsa_agent_dirichlet.py
usienarl/agents/tabular_expected_sarsa_agent_epsilon_greedy.py
usienarl/agents/tabular_q_learning_agent_boltzmann.py
usienarl/agents/tabular_q_learning_agent_dirichlet.py
usienarl/agents/tabular_q_learning_agent_epsilon_greedy.py
usienarl/agents/tabular_sarsa_agent_boltzmann.py
usienarl/agents/tabular_sarsa_agent_dirichlet.py
usienarl/agents/tabular_sarsa_agent_epsilon_greedy.py
usienarl/agents/vpg_agent.py
usienarl/interfaces/__init__.py
usienarl/interfaces/pass_through.py
usienarl/models/__init__.py
usienarl/models/deep_deterministic_policy_gradient.py
usienarl/models/deep_expected_sarsa.py
usienarl/models/deep_q_learning.py
usienarl/models/deep_sarsa.py
usienarl/models/double_deep_q_learning.py
