Metadata-Version: 2.1
Name: usienarl
Version: 0.7.8
Summary: University of Siena Reinforcement Learning library - SAILab
Home-page: https://github.com/InsaneMonster/USienaRL
Author: Luca Pasqualini
Author-email: pasqualini@diism.unisi.it
License: BSD 3-Clause
Keywords: Reinforcement Learning Reinforcement-Learning RL Machine Machine-Learning ML library framework SAILab USiena Siena
Platform: UNKNOWN
Classifier: Development Status :: 4 - Beta
Classifier: License :: OSI Approved :: BSD License
Classifier: Programming Language :: Python :: 3.6
Classifier: Topic :: Scientific/Engineering :: Artificial Intelligence
Provides-Extra: tensorflow
Provides-Extra: tensorflow_gpu
